sqlacrossover.py
sqlacrossover-0.3.2.dist-info/AUTHORS
sqlacrossover-0.3.2.dist-info/LICENSE
sqlacrossover-0.3.2.dist-info/METADATA
sqlacrossover-0.3.2.dist-info/WHEEL
sqlacrossover-0.3.2.dist-info/entry_points.txt
sqlacrossover-0.3.2.dist-info/pbr.json
sqlacrossover-0.3.2.dist-info/top_level.txt
sqlacrossover-0.3.2.dist-info/RECORD
