Metadata-Version: 2.1
Name: sqlacrossover
Version: 0.3.2
Summary: SQLAlchemy-based cross-database migration tool
Home-page: https://pypi.org/project/sqlacrossover/
Author: Andrew Grigorev
Author-email: andrew@ei-grad.ru
License: Apache-2
Project-URL: Bug Tracker, https://github.com/ei-grad/sqlacrossover/issues
Project-URL: Documentation, https://github.com/ei-grad/sqlacrossover
Project-URL: Source Code, https://github.com/ei-grad/sqlacrossover
Keywords: sqlalchemy,database migration,data migration
Platform: UNKNOWN
Classifier: Development Status :: 4 - Beta
Classifier: Environment :: Console
Classifier: Intended Audience :: Developers
Classifier: Intended Audience :: Information Technology
Classifier: Topic :: Database
Classifier: License :: OSI Approved :: Apache Software License
Classifier: Operating System :: OS Independent
Classifier: Programming Language :: Python
License-File: LICENSE
License-File: AUTHORS
Requires-Dist: sqlalchemy
Provides-Extra: mysql
Requires-Dist: pymysql ; extra == 'mysql'
Provides-Extra: postgresql
Requires-Dist: psycopg2 ; extra == 'postgresql'
